powerbanktau/__init__.py
powerbanktau/utils.py
powerbanktau-0.2.1.data/scripts/interactive_pbs.sh
powerbanktau-0.2.1.data/scripts/interactive_slurm.sh
powerbanktau-0.2.1.data/scripts/mount_project.sh
powerbanktau-0.2.1.data/scripts/pbs_notebook.sh
powerbanktau-0.2.1.data/scripts/slurm_gpu_notebook.sh
powerbanktau-0.2.1.data/scripts/slurm_notebook.sh
powerbanktau-0.2.1.dist-info/METADATA
powerbanktau-0.2.1.dist-info/WHEEL
powerbanktau-0.2.1.dist-info/top_level.txt
powerbanktau-0.2.1.dist-info/RECORD
