Metadata-Version: 2.1
Name: powerbanktau
Version: 0.2.1
Summary: Dask cluster utilities for HPC environments
Author: Nicolas Lynn
Author-email: nicolaslynn@mail.tau.ac.il
License: BSD 2-clause
Classifier: Development Status :: 3 - Alpha
Classifier: Intended Audience :: Science/Research
Classifier: License :: OSI Approved :: BSD License
Classifier: Operating System :: POSIX :: Linux
Classifier: Programming Language :: Python :: 3
Classifier: Programming Language :: Python :: 3.7
Classifier: Programming Language :: Python :: 3.8
Classifier: Programming Language :: Python :: 3.9
Classifier: Programming Language :: Python :: 3.10
Classifier: Programming Language :: Python :: 3.11
Classifier: Programming Language :: Python :: 3.12
Classifier: Topic :: Scientific/Engineering
Classifier: Topic :: System :: Clustering
Requires-Python: >=3.7
Requires-Dist: pandas
Requires-Dist: tqdm
Requires-Dist: dask
Requires-Dist: dask-jobqueue
Requires-Dist: psutil
Requires-Dist: numpy
Requires-Dist: pyarrow
Requires-Dist: tables
Requires-Dist: openpyxl
